{
	"configurations" : 
	[
		{
			"directories" : 
			[
				{
					"build" : ".",
					"jsonFile" : "directory-.-Debug-f5ebdc15457944623624.json",
					"minimumCMakeVersion" : 
					{
						"string" : "3.23"
					},
					"projectIndex" : 0,
					"source" : ".",
					"targetIndexes" : 
					[
						0
					]
				}
			],
			"name" : "Debug",
			"projects" : 
			[
				{
					"directoryIndexes" : 
					[
						0
					],
					"name" : "Ballot_Counter",
					"targetIndexes" : 
					[
						0
					]
				}
			],
			"targets" : 
			[
				{
					"directoryIndex" : 0,
					"id" : "Ballot_Counter::@6890427a1f51a3e7e1df",
					"jsonFile" : "target-Ballot_Counter-Debug-7430cfa6a14751f19717.json",
					"name" : "Ballot_Counter",
					"projectIndex" : 0
				}
			]
		}
	],
	"kind" : "codemodel",
	"paths" : 
	{
		"build" : "/Users/ukp66482/Desktop/CK judge/Ch 11/Ballot Counter/cmake-build-debug",
		"source" : "/Users/ukp66482/Desktop/CK judge/Ch 11/Ballot Counter"
	},
	"version" : 
	{
		"major" : 2,
		"minor" : 4
	}
}
