{
	"configurations" : 
	[
		{
			"directories" : 
			[
				{
					"build" : ".",
					"jsonFile" : "directory-.-Debug-f5ebdc15457944623624.json",
					"minimumCMakeVersion" : 
					{
						"string" : "3.23"
					},
					"projectIndex" : 0,
					"source" : ".",
					"targetIndexes" : 
					[
						0
					]
				}
			],
			"name" : "Debug",
			"projects" : 
			[
				{
					"directoryIndexes" : 
					[
						0
					],
					"name" : "______orz__orz______",
					"targetIndexes" : 
					[
						0
					]
				}
			],
			"targets" : 
			[
				{
					"directoryIndex" : 0,
					"id" : "______orz__orz______::@6890427a1f51a3e7e1df",
					"jsonFile" : "target-______orz__orz______-Debug-3db36d22e2ea9767cb9d.json",
					"name" : "______orz__orz______",
					"projectIndex" : 0
				}
			]
		}
	],
	"kind" : "codemodel",
	"paths" : 
	{
		"build" : "/Users/ukp66482/Desktop/CK judge/2022_midterm/!!!!!!orz \u6700\u5f37\u819c\u62dc orz!!!!!!/cmake-build-debug",
		"source" : "/Users/ukp66482/Desktop/CK judge/2022_midterm/!!!!!!orz \u6700\u5f37\u819c\u62dc orz!!!!!!"
	},
	"version" : 
	{
		"major" : 2,
		"minor" : 4
	}
}
